semester_6/verilog_lab/full_using_half.v
module full_adder(A,B,C,Carry,Sum);
input A,B,C;
output Carry,Sum;


wire x,y,z;



xor(z,A,B);
and(y,z,C);
and(x,A,B);

or(Carry,y,x);


xor(Sum,A,B,C);

endmodule

module Test;
reg a,b,c;
wire carry,sum;

full_adder fa(a,b,c,carry,sum);
initial begin
	$dumpfile("full_adder.vcd");
	$dumpvars(0,Test);
	$display("A B C Carry Sum");
	$monitor("%b %b %b \t %b   %b", a,b,c,carry,sum);
	a=0;b=0;c=0;
	#10 a=0;b=0;c=1;
	#10 a=0;b=1;c=0;
	#10 a=0;b=1;c=1;
	#10 a=1;b=0;c=0;
	#10 a=1;b=0;c=1;
	#10 a=1;b=1;c=0;
	#10 a=1;b=1;c=1;
	#10
	$finish;
	end
	endmodule

semester_6/verilog_lab/full_adder.vcd
$date
	Mon Jan 21 14:10:28 2019
$end
$version
	Icarus Verilog
$end
$timescale
	1s
$end
$scope module Test $end
$var wire 1 ! carry $end
$var wire 1 " sum $end
$var reg 1 # a $end
$var reg 1 $ b $end
$var reg 1 % c $end
$scope module fa $end
$var wire 1 & A $end
$var wire 1 ' B $end
$var wire 1 ( C $end
$var wire 1 ! Carry $end
$var wire 1 " Sum $end
$var wire 1 ) x $end
$var wire 1 * y $end
$var wire 1 + z $end
$upscope $end
$upscope $end
$enddefinitions $end
#0
$dumpvars
0+
0*
0)
0(
0'
0&
0%
0$
0#
0"
0!
$end
#10
1"
1%
1(
#20
1+
0%
0(
1$
1'
#30
1!
1*
0"
1%
1(
#40
0!
0*
1"
0%
0(
0$
0'
1#
1&
#50
1!
1*
0"
1%
1(
#60
0*
0+
1)
0%
0(
1$
1'
#70
1"
1%
1(
