verilog_lab/full_subtractor.v
module full_subtractor(A,B,C,Difference,Borrow);
input A,B,C;
output Difference,Borrow;


wire x,y,z,w,p,q,r;





xor(Difference,A,B,C);



and(p,~A,C);
and(q,~A,B);
and(r,B,C);

or(Borrow,p,q,r);




endmodule

module Test;
reg a,b,c;
wire difference,borrow;

full_subtractor fa(a,b,c,difference,borrow);
initial begin
	$dumpfile("full_subtractor.vcd");
	$dumpvars(0,Test);
	$display("A B C difference borrow");
	$monitor("%b %b %b \t %b   %b", a,b,c,difference,borrow);
	a=0;b=0;c=0;
	#10 a=0;b=0;c=1;
	#10 a=0;b=1;c=0;
	#10 a=0;b=1;c=1;
	#10 a=1;b=0;c=0;
	#10 a=1;b=0;c=1;
	#10 a=1;b=1;c=0;
	#10 a=1;b=1;c=1;
	#10
	$finish;
	end
	endmodule

verilog_lab/full_subtractor.vcd
$date
	Mon Jan 28 13:56:22 2019
$end
$version
	Icarus Verilog
$end
$timescale
	1s
$end
$scope module Test $end
$var wire 1 ! borrow $end
$var wire 1 " difference $end
$var reg 1 # a $end
$var reg 1 $ b $end
$var reg 1 % c $end
$scope module fa $end
$var wire 1 & A $end
$var wire 1 ' B $end
$var wire 1 ! Borrow $end
$var wire 1 ( C $end
$var wire 1 " Difference $end
$var wire 1 ) p $end
$var wire 1 * q $end
$var wire 1 + r $end
$upscope $end
$upscope $end
$enddefinitions $end
#0
$dumpvars
0+
0*
0)
0(
0'
0&
0%
0$
0#
0"
0!
$end
#10
1!
1"
1)
1%
1(
#20
0)
1*
0%
0(
1$
1'
#30
0"
1)
1+
1%
1(
#40
0!
0)
0*
0+
1"
0%
0(
0$
0'
1#
1&
#50
0"
1%
1(
#60
0%
0(
1$
1'
#70
1!
1"
1+
1%
1(
